src/id/registers.v
module registers(
    input clk,
    input rst,
    input wen,
    input [4:0] rs1,
    input [4:0] rs2,
    input [4:0] rd,
    input  [31:0] rd_v,
    output [31:0] rs1_v,
    output [31:0] rs2_v
);

integer i = 0;
reg [31:0] reg_files[31:0];

initial begin
    for(i = 0; i < 32; i = i + 1)
        reg_files[i] <= 32'b0;
end

always @(posedge clk or negedge rst) begin
    if(!rst) begin
        for(i = 0; i < 32; i = i + 1)
            reg_files[i] <= 32'b0; 
    end
end

always @(posedge clk) begin
    if(wen)
        reg_files[rd] <= rd_v;
end

assign rs1_v = reg_files[rs1];
assign rs2_v = reg_files[rs2];

endmodule

src/id/democe.v
module decode(
    input [31:0] inst,
    output [4:0] rs1,
    output [4:0] rs2,
    output [4:0] rd,
    output ctl,
    output reg [31:0] imm
);

`define OP_LUI          7'b0110111
`define OP_AUIPC        7'b0010111  
`define OP_JAL          7'b1101111  
`define OP_JALR         7'b1100111  
`define OP_B            7'b1100011  
`define OP_LOAD         7'b0000011  
`define OP_SAVE         7'b0100011  
`define OP_ALUI         7'b0010011
`define OP_ALU          7'b0110011

wire [6:0] opcode = inst[6:0];
wire [4:0] rs2 = inst[24:20];
wire [4:0] rs1 = inst[19:15];
wire [4:0] rd  = inst[11:7];
wire [2:0] funct3 = inst[14:12];
wire [6:0] funct7 = inst[31:25];

wire [31:0] imm_i = {{20{inst[31]}}, inst[31:20]};
wire [31:0] imm_s = {{20{inst[31]}}, inst[31:25], inst[11:7]};
wire [31:0] imm_b = {{20{inst[31]}}, inst[31], inst[7], inst[30:25], inst[11:8]};
wire [31:0] imm_u = {inst[31:12], {12{1'b0}}};
wire [31:0] imm_j = {{12{inst[31]}}, inst[31], inst[19:12], inst[20], inst[30:21]};

// out put the imm
always @(*) begin
    case(opcode)
        7'b0110111:        imm <= imm_u;
        7'b0010111:        imm <= imm_u;
        7'b1101111:        imm <= imm_j;
        7'b1100111:        imm <= imm_i;
        7'b1100011:        imm <= imm_b;
        7'b0000011:        imm <= imm_i;
        7'b0100011:        imm <= imm_s;
        7'b0010011:        imm <= imm_i;
        7'b0110011:        imm <= 32'd0;
        default:        imm <= 32'd0;
    endcase
end

endmodule

src/id/id.v
module id(
    input clk,
    input rst,
    input [31:0] pc,
    input [31:0] inst
);

wire [31:0] imm;
wire ctl;
wire [4:0] rs1;
wire [4:0] rs2;
wire [4:0] rd;
wire [31:0] rs1_v;
wire [31:0] rs2_v;
wire [31:0] rd_v;

decode decode_u(
    .inst(inst),
    .rs1(rs1),
    .rs2(rs2),
    .rd(rd),
    .ctl(ctl),
    .imm(imm)
);

registers regs_u(
    .clk(clk),
    .rst(rst),
    .wen(1),
    .rs1(rs1),
    .rs2(rs2),
    .rd(rd),
    .rd_v(rd_v),
    .rs1_v(rs1_v),
    .rs2_v(rs2_v)
);



endmodule

src/if_id.v
module if_id(
    input clk,
    input rst,
    input [31:0] pc,
    input [31:0] inst,
    output reg [31:0] pc_out,
    output reg [31:0] inst_out
);

always @(posedge clk or negedge rst) begin
    if(!rst) begin
        pc_out <= 32'd0;
        inst_out <= 32'd0;
    end else begin
        pc_out <= pc;
        inst_out <= inst;
    end
end

endmodule

src/if/pc.v
module pc(
    input clk,
    input rst,
    output [31:0] pc_out
);

    reg [31:0] pc = 32'h80000000;
    always @(posedge clk or negedge rst) begin
        if(!rst) begin
            pc <= 32'h80000000;
        end else begin
            pc <= pc + 4;
        end
    end

    assign pc_out = pc;

endmodule

src/if/if.v
module ifs(
    input clk,
    input rst,
    output [31:0] pc,
    output [31:0] inst
);

wire [31:0] pc;
wire [31:0] inst;
assign inst = 32'h00508113;

pc pc_u(
    .clk(clk),
    .rst(rst),
    .pc_out(pc)
);

endmodule

src/core.v
module core(
    input clk,
    input rst
);

wire [31:0] pc;
wire [31:0] inst;
wire [31:0] pc_out;
wire [31:0] inst_out;

ifs if_u(
    .clk(clk),
    .rst(rst),
    .pc(pc),
    .inst(inst)
);

if_id if_id_u(
    .clk(clk),
    .rst(rst),
    .pc(pc),
    .inst(inst),
    .pc_out(pc_out),
    .inst_out(inst_out)
);

id id_u(
    .clk(clk),
    .rst(rst),
    .pc(pc_out),
    .inst(inst_out)
);



endmodule

tests/core_tb.v
module test();

    reg clk = 0;
    reg rst = 0;

    initial begin
        rst = 0;
        #100; 
        rst = 1;
        #100;
        $finish;
    end

    always begin
        #1 clk = ~clk;
    end

    core core_u(
        .clk(clk),
        .rst(rst)
    );

    initial begin 
        $dumpfile("build/wave.vcd");
        $dumpvars(0, test);
    end

endmodule

build/wave.vcd
$date
	Sat Mar 23 22:01:20 2024
$end
$version
	Icarus Verilog
$end
$timescale
	1s
$end
$scope module test $end
$var reg 1 ! clk $end
$var reg 1 " rst $end
$scope module core_u $end
$var wire 1 ! clk $end
$var wire 32 # inst [31:0] $end
$var wire 1 " rst $end
$var wire 32 $ pc_out [31:0] $end
$var wire 32 % pc [31:0] $end
$var wire 32 & inst_out [31:0] $end
$scope module id_u $end
$var wire 1 ! clk $end
$var wire 1 ' ctl $end
$var wire 32 ( rd_v [31:0] $end
$var wire 1 " rst $end
$var wire 32 ) rs2_v [31:0] $end
$var wire 5 * rs2 [4:0] $end
$var wire 32 + rs1_v [31:0] $end
$var wire 5 , rs1 [4:0] $end
$var wire 5 - rd [4:0] $end
$var wire 32 . pc [31:0] $end
$var wire 32 / inst [31:0] $end
$var wire 32 0 imm [31:0] $end
$scope module decode_u $end
$var wire 1 ' ctl $end
$var wire 5 1 rs2 [4:0] $end
$var wire 5 2 rs1 [4:0] $end
$var wire 5 3 rd [4:0] $end
$var wire 7 4 opcode [6:0] $end
$var wire 32 5 inst [31:0] $end
$var wire 32 6 imm_u [31:0] $end
$var wire 32 7 imm_s [31:0] $end
$var wire 32 8 imm_j [31:0] $end
$var wire 32 9 imm_i [31:0] $end
$var wire 32 : imm_b [31:0] $end
$var wire 7 ; funct7 [6:0] $end
$var wire 3 < funct3 [2:0] $end
$var reg 32 = imm [31:0] $end
$upscope $end
$scope module regs_u $end
$var wire 1 ! clk $end
$var wire 5 > rd [4:0] $end
$var wire 32 ? rd_v [31:0] $end
$var wire 5 @ rs1 [4:0] $end
$var wire 32 A rs1_v [31:0] $end
$var wire 5 B rs2 [4:0] $end
$var wire 32 C rs2_v [31:0] $end
$var wire 1 " rst $end
$var wire 1 D wen $end
$var integer 32 E i [31:0] $end
$upscope $end
$upscope $end
$scope module if_id_u $end
$var wire 1 ! clk $end
$var wire 32 F inst [31:0] $end
$var wire 1 " rst $end
$var wire 32 G pc [31:0] $end
$var reg 32 H inst_out [31:0] $end
$var reg 32 I pc_out [31:0] $end
$upscope $end
$scope module if_u $end
$var wire 1 ! clk $end
$var wire 32 J inst [31:0] $end
$var wire 1 " rst $end
$var wire 32 K pc [31:0] $end
$scope module pc_u $end
$var wire 1 ! clk $end
$var wire 32 L pc_out [31:0] $end
$var wire 1 " rst $end
$var reg 32 M pc [31:0] $end
$upscope $end
$upscope $end
$upscope $end
$upscope $end
$enddefinitions $end
#0
$dumpvars
b10000000000000000000000000000000 M
b10000000000000000000000000000000 L
b10000000000000000000000000000000 K
b10100001000000100010011 J
b0 I
b0 H
b10000000000000000000000000000000 G
b10100001000000100010011 F
b100000 E
1D
b0 C
b0 B
b0 A
b0 @
b1100000011000000110000001100000 ?
b0 >
b0 =
b0 <
b0 ;
b0 :
b0 9
b0 8
b0 7
b0 6
b0 5
b0 4
b0 3
b0 2
b0 1
b0 0
b0 /
b0 .
b0 -
b0 ,
b0 +
b0 *
b0 )
b1100000011000000110000001100000 (
z'
b0 &
b10000000000000000000000000000000 %
b0 $
b10100001000000100010011 #
0"
0!
$end
#1
b1100000011000000110000001100000 +
b1100000011000000110000001100000 A
b1100000011000000110000001100000 )
b1100000011000000110000001100000 C
b100000 E
1!
#2
0!
#3
b1100000011000000110000001100000 +
b1100000011000000110000001100000 A
b1100000011000000110000001100000 )
b1100000011000000110000001100000 C
b100000 E
1!
#4
0!
#5
b1100000011000000110000001100000 +
b1100000011000000110000001100000 A
b1100000011000000110000001100000 )
b1100000011000000110000001100000 C
b100000 E
1!
#6
0!
#7
b1100000011000000110000001100000 +
b1100000011000000110000001100000 A
b1100000011000000110000001100000 )
b1100000011000000110000001100000 C
b100000 E
1!
#8
0!
#9
b1100000011000000110000001100000 +
b1100000011000000110000001100000 A
b1100000011000000110000001100000 )
b1100000011000000110000001100000 C
b100000 E
1!
#10
0!
#11
b1100000011000000110000001100000 +
b1100000011000000110000001100000 A
b1100000011000000110000001100000 )
b1100000011000000110000001100000 C
b100000 E
1!
#12
0!
#13
b1100000011000000110000001100000 +
b1100000011000000110000001100000 A
b1100000011000000110000001100000 )
b1100000011000000110000001100000 C
b100000 E
1!
#14
0!
#15
b1100000011000000110000001100000 +
b1100000011000000110000001100000 A
b1100000011000000110000001100000 )
b1100000011000000110000001100000 C
b100000 E
1!
#16
0!
#17
b1100000011000000110000001100000 +
b1100000011000000110000001100000 A
b1100000011000000110000001100000 )
b1100000011000000110000001100000 C
b100000 E
1!
#18
0!
#19
b1100000011000000110000001100000 +
b1100000011000000110000001100000 A
b1100000011000000110000001100000 )
b1100000011000000110000001100000 C
b100000 E
1!
#20
0!
#21
b1100000011000000110000001100000 +
b1100000011000000110000001100000 A
b1100000011000000110000001100000 )
b1100000011000000110000001100000 C
b100000 E
1!
#22
0!
#23
b1100000011000000110000001100000 +
b1100000011000000110000001100000 A
b1100000011000000110000001100000 )
b1100000011000000110000001100000 C
b100000 E
1!
#24
0!
#25
b1100000011000000110000001100000 +
b1100000011000000110000001100000 A
b1100000011000000110000001100000 )
b1100000011000000110000001100000 C
b100000 E
1!
#26
0!
#27
b1100000011000000110000001100000 +
b1100000011000000110000001100000 A
b1100000011000000110000001100000 )
b1100000011000000110000001100000 C
b100000 E
1!
#28
0!
#29
b1100000011000000110000001100000 +
b1100000011000000110000001100000 A
b1100000011000000110000001100000 )
b1100000011000000110000001100000 C
b100000 E
1!
#30
0!
#31
b1100000011000000110000001100000 +
b1100000011000000110000001100000 A
b1100000011000000110000001100000 )
b1100000011000000110000001100000 C
b100000 E
1!
#32
0!
#33
b1100000011000000110000001100000 +
b1100000011000000110000001100000 A
b1100000011000000110000001100000 )
b1100000011000000110000001100000 C
b100000 E
1!
#34
0!
#35
b1100000011000000110000001100000 +
b1100000011000000110000001100000 A
b1100000011000000110000001100000 )
b1100000011000000110000001100000 C
b100000 E
1!
#36
0!
#37
b1100000011000000110000001100000 +
b1100000011000000110000001100000 A
b1100000011000000110000001100000 )
b1100000011000000110000001100000 C
b100000 E
1!
#38
0!
#39
b1100000011000000110000001100000 +
b1100000011000000110000001100000 A
b1100000011000000110000001100000 )
b1100000011000000110000001100000 C
b100000 E
1!
#40
0!
#41
b1100000011000000110000001100000 +
b1100000011000000110000001100000 A
b1100000011000000110000001100000 )
b1100000011000000110000001100000 C
b100000 E
1!
#42
0!
#43
b1100000011000000110000001100000 +
b1100000011000000110000001100000 A
b1100000011000000110000001100000 )
b1100000011000000110000001100000 C
b100000 E
1!
#44
0!
#45
b1100000011000000110000001100000 +
b1100000011000000110000001100000 A
b1100000011000000110000001100000 )
b1100000011000000110000001100000 C
b100000 E
1!
#46
0!
#47
b1100000011000000110000001100000 +
b1100000011000000110000001100000 A
b1100000011000000110000001100000 )
b1100000011000000110000001100000 C
b100000 E
1!
#48
0!
#49
b1100000011000000110000001100000 +
b1100000011000000110000001100000 A
b1100000011000000110000001100000 )
b1100000011000000110000001100000 C
b100000 E
1!
#50
0!
#51
b1100000011000000110000001100000 +
b1100000011000000110000001100000 A
b1100000011000000110000001100000 )
b1100000011000000110000001100000 C
b100000 E
1!
#52
0!
#53
b1100000011000000110000001100000 +
b1100000011000000110000001100000 A
b1100000011000000110000001100000 )
b1100000011000000110000001100000 C
b100000 E
1!
#54
0!
#55
b1100000011000000110000001100000 +
b1100000011000000110000001100000 A
b1100000011000000110000001100000 )
b1100000011000000110000001100000 C
b100000 E
1!
#56
0!
#57
b1100000011000000110000001100000 +
b1100000011000000110000001100000 A
b1100000011000000110000001100000 )
b1100000011000000110000001100000 C
b100000 E
1!
#58
0!
#59
b1100000011000000110000001100000 +
b1100000011000000110000001100000 A
b1100000011000000110000001100000 )
b1100000011000000110000001100000 C
b100000 E
1!
#60
0!
#61
b1100000011000000110000001100000 +
b1100000011000000110000001100000 A
b1100000011000000110000001100000 )
b1100000011000000110000001100000 C
b100000 E
1!
#62
0!
#63
b1100000011000000110000001100000 +
b1100000011000000110000001100000 A
b1100000011000000110000001100000 )
b1100000011000000110000001100000 C
b100000 E
1!
#64
0!
#65
b1100000011000000110000001100000 +
b1100000011000000110000001100000 A
b1100000011000000110000001100000 )
b1100000011000000110000001100000 C
b100000 E
1!
#66
0!
#67
b1100000011000000110000001100000 +
b1100000011000000110000001100000 A
b1100000011000000110000001100000 )
b1100000011000000110000001100000 C
b100000 E
1!
#68
0!
#69
b1100000011000000110000001100000 +
b1100000011000000110000001100000 A
b1100000011000000110000001100000 )
b1100000011000000110000001100000 C
b100000 E
1!
#70
0!
#71
b1100000011000000110000001100000 +
b1100000011000000110000001100000 A
b1100000011000000110000001100000 )
b1100000011000000110000001100000 C
b100000 E
1!
#72
0!
#73
b1100000011000000110000001100000 +
b1100000011000000110000001100000 A
b1100000011000000110000001100000 )
b1100000011000000110000001100000 C
b100000 E
1!
#74
0!
#75
b1100000011000000110000001100000 +
b1100000011000000110000001100000 A
b1100000011000000110000001100000 )
b1100000011000000110000001100000 C
b100000 E
1!
#76
0!
#77
b1100000011000000110000001100000 +
b1100000011000000110000001100000 A
b1100000011000000110000001100000 )
b1100000011000000110000001100000 C
b100000 E
1!
#78
0!
#79
b1100000011000000110000001100000 +
b1100000011000000110000001100000 A
b1100000011000000110000001100000 )
b1100000011000000110000001100000 C
b100000 E
1!
#80
0!
#81
b1100000011000000110000001100000 +
b1100000011000000110000001100000 A
b1100000011000000110000001100000 )
b1100000011000000110000001100000 C
b100000 E
1!
#82
0!
#83
b1100000011000000110000001100000 +
b1100000011000000110000001100000 A
b1100000011000000110000001100000 )
b1100000011000000110000001100000 C
b100000 E
1!
#84
0!
#85
b1100000011000000110000001100000 +
b1100000011000000110000001100000 A
b1100000011000000110000001100000 )
b1100000011000000110000001100000 C
b100000 E
1!
#86
0!
#87
b1100000011000000110000001100000 +
b1100000011000000110000001100000 A
b1100000011000000110000001100000 )
b1100000011000000110000001100000 C
b100000 E
1!
#88
0!
#89
b1100000011000000110000001100000 +
b1100000011000000110000001100000 A
b1100000011000000110000001100000 )
b1100000011000000110000001100000 C
b100000 E
1!
#90
0!
#91
b1100000011000000110000001100000 +
b1100000011000000110000001100000 A
b1100000011000000110000001100000 )
b1100000011000000110000001100000 C
b100000 E
1!
#92
0!
#93
b1100000011000000110000001100000 +
b1100000011000000110000001100000 A
b1100000011000000110000001100000 )
b1100000011000000110000001100000 C
b100000 E
1!
#94
0!
#95
b1100000011000000110000001100000 +
b1100000011000000110000001100000 A
b1100000011000000110000001100000 )
b1100000011000000110000001100000 C
b100000 E
1!
#96
0!
#97
b1100000011000000110000001100000 +
b1100000011000000110000001100000 A
b1100000011000000110000001100000 )
b1100000011000000110000001100000 C
b100000 E
1!
#98
0!
#99
b1100000011000000110000001100000 +
b1100000011000000110000001100000 A
b1100000011000000110000001100000 )
b1100000011000000110000001100000 C
b100000 E
1!
#100
0!
1"
#101
b101 0
b101 =
b100010000000010 8
b10100001000000000000000 6
b1 :
b10 7
b101 9
b10 -
b10 3
b10 >
b0 +
b0 A
b1 ,
b1 2
b1 @
b0 )
b0 C
b101 *
b101 1
b101 B
b10011 4
b10100001000000100010011 &
b10100001000000100010011 /
b10100001000000100010011 5
b10100001000000100010011 H
b10000000000000000000000000000000 $
b10000000000000000000000000000000 .
b10000000000000000000000000000000 I
b10000000000000000000000000000100 %
b10000000000000000000000000000100 G
b10000000000000000000000000000100 K
b10000000000000000000000000000100 L
b10000000000000000000000000000100 M
1!
#102
0!
#103
b10000000000000000000000000001000 %
b10000000000000000000000000001000 G
b10000000000000000000000000001000 K
b10000000000000000000000000001000 L
b10000000000000000000000000001000 M
b10000000000000000000000000000100 $
b10000000000000000000000000000100 .
b10000000000000000000000000000100 I
1!
#104
0!
#105
b10000000000000000000000000001000 $
b10000000000000000000000000001000 .
b10000000000000000000000000001000 I
b10000000000000000000000000001100 %
b10000000000000000000000000001100 G
b10000000000000000000000000001100 K
b10000000000000000000000000001100 L
b10000000000000000000000000001100 M
1!
#106
0!
#107
b10000000000000000000000000010000 %
b10000000000000000000000000010000 G
b10000000000000000000000000010000 K
b10000000000000000000000000010000 L
b10000000000000000000000000010000 M
b10000000000000000000000000001100 $
b10000000000000000000000000001100 .
b10000000000000000000000000001100 I
1!
#108
0!
#109
b10000000000000000000000000010000 $
b10000000000000000000000000010000 .
b10000000000000000000000000010000 I
b10000000000000000000000000010100 %
b10000000000000000000000000010100 G
b10000000000000000000000000010100 K
b10000000000000000000000000010100 L
b10000000000000000000000000010100 M
1!
#110
0!
#111
b10000000000000000000000000011000 %
b10000000000000000000000000011000 G
b10000000000000000000000000011000 K
b10000000000000000000000000011000 L
b10000000000000000000000000011000 M
b10000000000000000000000000010100 $
b10000000000000000000000000010100 .
b10000000000000000000000000010100 I
1!
#112
0!
#113
b10000000000000000000000000011000 $
b10000000000000000000000000011000 .
b10000000000000000000000000011000 I
b10000000000000000000000000011100 %
b10000000000000000000000000011100 G
b10000000000000000000000000011100 K
b10000000000000000000000000011100 L
b10000000000000000000000000011100 M
1!
#114
0!
#115
b10000000000000000000000000100000 %
b10000000000000000000000000100000 G
b10000000000000000000000000100000 K
b10000000000000000000000000100000 L
b10000000000000000000000000100000 M
b10000000000000000000000000011100 $
b10000000000000000000000000011100 .
b10000000000000000000000000011100 I
1!
#116
0!
#117
b10000000000000000000000000100000 $
b10000000000000000000000000100000 .
b10000000000000000000000000100000 I
b10000000000000000000000000100100 %
b10000000000000000000000000100100 G
b10000000000000000000000000100100 K
b10000000000000000000000000100100 L
b10000000000000000000000000100100 M
1!
#118
0!
#119
b10000000000000000000000000101000 %
b10000000000000000000000000101000 G
b10000000000000000000000000101000 K
b10000000000000000000000000101000 L
b10000000000000000000000000101000 M
b10000000000000000000000000100100 $
b10000000000000000000000000100100 .
b10000000000000000000000000100100 I
1!
#120
0!
#121
b10000000000000000000000000101000 $
b10000000000000000000000000101000 .
b10000000000000000000000000101000 I
b10000000000000000000000000101100 %
b10000000000000000000000000101100 G
b10000000000000000000000000101100 K
b10000000000000000000000000101100 L
b10000000000000000000000000101100 M
1!
#122
0!
#123
b10000000000000000000000000110000 %
b10000000000000000000000000110000 G
b10000000000000000000000000110000 K
b10000000000000000000000000110000 L
b10000000000000000000000000110000 M
b10000000000000000000000000101100 $
b10000000000000000000000000101100 .
b10000000000000000000000000101100 I
1!
#124
0!
#125
b10000000000000000000000000110000 $
b10000000000000000000000000110000 .
b10000000000000000000000000110000 I
b10000000000000000000000000110100 %
b10000000000000000000000000110100 G
b10000000000000000000000000110100 K
b10000000000000000000000000110100 L
b10000000000000000000000000110100 M
1!
#126
0!
#127
b10000000000000000000000000111000 %
b10000000000000000000000000111000 G
b10000000000000000000000000111000 K
b10000000000000000000000000111000 L
b10000000000000000000000000111000 M
b10000000000000000000000000110100 $
b10000000000000000000000000110100 .
b10000000000000000000000000110100 I
1!
#128
0!
#129
b10000000000000000000000000111000 $
b10000000000000000000000000111000 .
b10000000000000000000000000111000 I
b10000000000000000000000000111100 %
b10000000000000000000000000111100 G
b10000000000000000000000000111100 K
b10000000000000000000000000111100 L
b10000000000000000000000000111100 M
1!
#130
0!
#131
b10000000000000000000000001000000 %
b10000000000000000000000001000000 G
b10000000000000000000000001000000 K
b10000000000000000000000001000000 L
b10000000000000000000000001000000 M
b10000000000000000000000000111100 $
b10000000000000000000000000111100 .
b10000000000000000000000000111100 I
1!
#132
0!
#133
b10000000000000000000000001000000 $
b10000000000000000000000001000000 .
b10000000000000000000000001000000 I
b10000000000000000000000001000100 %
b10000000000000000000000001000100 G
b10000000000000000000000001000100 K
b10000000000000000000000001000100 L
b10000000000000000000000001000100 M
1!
#134
0!
#135
b10000000000000000000000001001000 %
b10000000000000000000000001001000 G
b10000000000000000000000001001000 K
b10000000000000000000000001001000 L
b10000000000000000000000001001000 M
b10000000000000000000000001000100 $
b10000000000000000000000001000100 .
b10000000000000000000000001000100 I
1!
#136
0!
#137
b10000000000000000000000001001000 $
b10000000000000000000000001001000 .
b10000000000000000000000001001000 I
b10000000000000000000000001001100 %
b10000000000000000000000001001100 G
b10000000000000000000000001001100 K
b10000000000000000000000001001100 L
b10000000000000000000000001001100 M
1!
#138
0!
#139
b10000000000000000000000001010000 %
b10000000000000000000000001010000 G
b10000000000000000000000001010000 K
b10000000000000000000000001010000 L
b10000000000000000000000001010000 M
b10000000000000000000000001001100 $
b10000000000000000000000001001100 .
b10000000000000000000000001001100 I
1!
#140
0!
#141
b10000000000000000000000001010000 $
b10000000000000000000000001010000 .
b10000000000000000000000001010000 I
b10000000000000000000000001010100 %
b10000000000000000000000001010100 G
b10000000000000000000000001010100 K
b10000000000000000000000001010100 L
b10000000000000000000000001010100 M
1!
#142
0!
#143
b10000000000000000000000001011000 %
b10000000000000000000000001011000 G
b10000000000000000000000001011000 K
b10000000000000000000000001011000 L
b10000000000000000000000001011000 M
b10000000000000000000000001010100 $
b10000000000000000000000001010100 .
b10000000000000000000000001010100 I
1!
#144
0!
#145
b10000000000000000000000001011000 $
b10000000000000000000000001011000 .
b10000000000000000000000001011000 I
b10000000000000000000000001011100 %
b10000000000000000000000001011100 G
b10000000000000000000000001011100 K
b10000000000000000000000001011100 L
b10000000000000000000000001011100 M
1!
#146
0!
#147
b10000000000000000000000001100000 %
b10000000000000000000000001100000 G
b10000000000000000000000001100000 K
b10000000000000000000000001100000 L
b10000000000000000000000001100000 M
b10000000000000000000000001011100 $
b10000000000000000000000001011100 .
b10000000000000000000000001011100 I
1!
#148
0!
#149
b10000000000000000000000001100000 $
b10000000000000000000000001100000 .
b10000000000000000000000001100000 I
b10000000000000000000000001100100 %
b10000000000000000000000001100100 G
b10000000000000000000000001100100 K
b10000000000000000000000001100100 L
b10000000000000000000000001100100 M
1!
#150
0!
#151
b10000000000000000000000001101000 %
b10000000000000000000000001101000 G
b10000000000000000000000001101000 K
b10000000000000000000000001101000 L
b10000000000000000000000001101000 M
b10000000000000000000000001100100 $
b10000000000000000000000001100100 .
b10000000000000000000000001100100 I
1!
#152
0!
#153
b10000000000000000000000001101000 $
b10000000000000000000000001101000 .
b10000000000000000000000001101000 I
b10000000000000000000000001101100 %
b10000000000000000000000001101100 G
b10000000000000000000000001101100 K
b10000000000000000000000001101100 L
b10000000000000000000000001101100 M
1!
#154
0!
#155
b10000000000000000000000001110000 %
b10000000000000000000000001110000 G
b10000000000000000000000001110000 K
b10000000000000000000000001110000 L
b10000000000000000000000001110000 M
b10000000000000000000000001101100 $
b10000000000000000000000001101100 .
b10000000000000000000000001101100 I
1!
#156
0!
#157
b10000000000000000000000001110000 $
b10000000000000000000000001110000 .
b10000000000000000000000001110000 I
b10000000000000000000000001110100 %
b10000000000000000000000001110100 G
b10000000000000000000000001110100 K
b10000000000000000000000001110100 L
b10000000000000000000000001110100 M
1!
#158
0!
#159
b10000000000000000000000001111000 %
b10000000000000000000000001111000 G
b10000000000000000000000001111000 K
b10000000000000000000000001111000 L
b10000000000000000000000001111000 M
b10000000000000000000000001110100 $
b10000000000000000000000001110100 .
b10000000000000000000000001110100 I
1!
#160
0!
#161
b10000000000000000000000001111000 $
b10000000000000000000000001111000 .
b10000000000000000000000001111000 I
b10000000000000000000000001111100 %
b10000000000000000000000001111100 G
b10000000000000000000000001111100 K
b10000000000000000000000001111100 L
b10000000000000000000000001111100 M
1!
#162
0!
#163
b10000000000000000000000010000000 %
b10000000000000000000000010000000 G
b10000000000000000000000010000000 K
b10000000000000000000000010000000 L
b10000000000000000000000010000000 M
b10000000000000000000000001111100 $
b10000000000000000000000001111100 .
b10000000000000000000000001111100 I
1!
#164
0!
#165
b10000000000000000000000010000000 $
b10000000000000000000000010000000 .
b10000000000000000000000010000000 I
b10000000000000000000000010000100 %
b10000000000000000000000010000100 G
b10000000000000000000000010000100 K
b10000000000000000000000010000100 L
b10000000000000000000000010000100 M
1!
#166
0!
#167
b10000000000000000000000010001000 %
b10000000000000000000000010001000 G
b10000000000000000000000010001000 K
b10000000000000000000000010001000 L
b10000000000000000000000010001000 M
b10000000000000000000000010000100 $
b10000000000000000000000010000100 .
b10000000000000000000000010000100 I
1!
#168
0!
#169
b10000000000000000000000010001000 $
b10000000000000000000000010001000 .
b10000000000000000000000010001000 I
b10000000000000000000000010001100 %
b10000000000000000000000010001100 G
b10000000000000000000000010001100 K
b10000000000000000000000010001100 L
b10000000000000000000000010001100 M
1!
#170
0!
#171
b10000000000000000000000010010000 %
b10000000000000000000000010010000 G
b10000000000000000000000010010000 K
b10000000000000000000000010010000 L
b10000000000000000000000010010000 M
b10000000000000000000000010001100 $
b10000000000000000000000010001100 .
b10000000000000000000000010001100 I
1!
#172
0!
#173
b10000000000000000000000010010000 $
b10000000000000000000000010010000 .
b10000000000000000000000010010000 I
b10000000000000000000000010010100 %
b10000000000000000000000010010100 G
b10000000000000000000000010010100 K
b10000000000000000000000010010100 L
b10000000000000000000000010010100 M
1!
#174
0!
#175
b10000000000000000000000010011000 %
b10000000000000000000000010011000 G
b10000000000000000000000010011000 K
b10000000000000000000000010011000 L
b10000000000000000000000010011000 M
b10000000000000000000000010010100 $
b10000000000000000000000010010100 .
b10000000000000000000000010010100 I
1!
#176
0!
#177
b10000000000000000000000010011000 $
b10000000000000000000000010011000 .
b10000000000000000000000010011000 I
b10000000000000000000000010011100 %
b10000000000000000000000010011100 G
b10000000000000000000000010011100 K
b10000000000000000000000010011100 L
b10000000000000000000000010011100 M
1!
#178
0!
#179
b10000000000000000000000010100000 %
b10000000000000000000000010100000 G
b10000000000000000000000010100000 K
b10000000000000000000000010100000 L
b10000000000000000000000010100000 M
b10000000000000000000000010011100 $
b10000000000000000000000010011100 .
b10000000000000000000000010011100 I
1!
#180
0!
#181
b10000000000000000000000010100000 $
b10000000000000000000000010100000 .
b10000000000000000000000010100000 I
b10000000000000000000000010100100 %
b10000000000000000000000010100100 G
b10000000000000000000000010100100 K
b10000000000000000000000010100100 L
b10000000000000000000000010100100 M
1!
#182
0!
#183
b10000000000000000000000010101000 %
b10000000000000000000000010101000 G
b10000000000000000000000010101000 K
b10000000000000000000000010101000 L
b10000000000000000000000010101000 M
b10000000000000000000000010100100 $
b10000000000000000000000010100100 .
b10000000000000000000000010100100 I
1!
#184
0!
#185
b10000000000000000000000010101000 $
b10000000000000000000000010101000 .
b10000000000000000000000010101000 I
b10000000000000000000000010101100 %
b10000000000000000000000010101100 G
b10000000000000000000000010101100 K
b10000000000000000000000010101100 L
b10000000000000000000000010101100 M
1!
#186
0!
#187
b10000000000000000000000010110000 %
b10000000000000000000000010110000 G
b10000000000000000000000010110000 K
b10000000000000000000000010110000 L
b10000000000000000000000010110000 M
b10000000000000000000000010101100 $
b10000000000000000000000010101100 .
b10000000000000000000000010101100 I
1!
#188
0!
#189
b10000000000000000000000010110000 $
b10000000000000000000000010110000 .
b10000000000000000000000010110000 I
b10000000000000000000000010110100 %
b10000000000000000000000010110100 G
b10000000000000000000000010110100 K
b10000000000000000000000010110100 L
b10000000000000000000000010110100 M
1!
#190
0!
#191
b10000000000000000000000010111000 %
b10000000000000000000000010111000 G
b10000000000000000000000010111000 K
b10000000000000000000000010111000 L
b10000000000000000000000010111000 M
b10000000000000000000000010110100 $
b10000000000000000000000010110100 .
b10000000000000000000000010110100 I
1!
#192
0!
#193
b10000000000000000000000010111000 $
b10000000000000000000000010111000 .
b10000000000000000000000010111000 I
b10000000000000000000000010111100 %
b10000000000000000000000010111100 G
b10000000000000000000000010111100 K
b10000000000000000000000010111100 L
b10000000000000000000000010111100 M
1!
#194
0!
#195
b10000000000000000000000011000000 %
b10000000000000000000000011000000 G
b10000000000000000000000011000000 K
b10000000000000000000000011000000 L
b10000000000000000000000011000000 M
b10000000000000000000000010111100 $
b10000000000000000000000010111100 .
b10000000000000000000000010111100 I
1!
#196
0!
#197
b10000000000000000000000011000000 $
b10000000000000000000000011000000 .
b10000000000000000000000011000000 I
b10000000000000000000000011000100 %
b10000000000000000000000011000100 G
b10000000000000000000000011000100 K
b10000000000000000000000011000100 L
b10000000000000000000000011000100 M
1!
#198
0!
#199
b10000000000000000000000011001000 %
b10000000000000000000000011001000 G
b10000000000000000000000011001000 K
b10000000000000000000000011001000 L
b10000000000000000000000011001000 M
b10000000000000000000000011000100 $
b10000000000000000000000011000100 .
b10000000000000000000000011000100 I
1!
